commitizen_ruby/__init__.py
commitizen_ruby/ruby_version_provider.py
commitizen_ruby-0.2.0.dist-info/LICENSE
commitizen_ruby-0.2.0.dist-info/METADATA
commitizen_ruby-0.2.0.dist-info/WHEEL
commitizen_ruby-0.2.0.dist-info/entry_points.txt
commitizen_ruby-0.2.0.dist-info/RECORD
