Metadata-Version: 2.1
Name: commitizen-ruby
Version: 0.2.0
Summary: Commitizen version provider for Ruby gems/projects.
Author: Karsten Silkenbäumer
Author-email: 993392+kassi@users.noreply.github.com
Requires-Python: >=3.12,<4.0
Classifier: Programming Language :: Python :: 3
Classifier: Programming Language :: Python :: 3.12
Requires-Dist: deepmerge (>=1.1.1,<2.0.0)
